individual/main.py
individual/api/google_api.py
individual/api/opendb_api.py
individual/api/opensearch_api.py
individual/api/rakuten_api.py
individual/api/sru_api.py
individual/data_fix/matome_jikkou.py
individual_book_isbn_api-0.1.4.dist-info/LICENSE
individual_book_isbn_api-0.1.4.dist-info/METADATA
individual_book_isbn_api-0.1.4.dist-info/WHEEL
individual_book_isbn_api-0.1.4.dist-info/entry_points.txt
individual_book_isbn_api-0.1.4.dist-info/top_level.txt
individual_book_isbn_api-0.1.4.dist-info/RECORD
