Metadata-Version: 2.1
Name: individual_book_isbn_api
Version: 0.1.4
Summary: A project to gather and process book data from various sources
Author-email: Your Name <your.email@example.com>
License: MIT
Project-URL: Homepage, https://yourproject.com
Project-URL: Repository, https://github.com/yourusername/individual
Requires-Python: >=3.8
License-File: LICENSE
Requires-Dist: aiofiles ==24.1.0
Requires-Dist: aiohappyeyeballs ==2.3.4
Requires-Dist: aiohttp ==3.10.1
Requires-Dist: aiosignal ==1.3.1
Requires-Dist: async-timeout ==4.0.3
Requires-Dist: attrs ==24.2.0
Requires-Dist: blinker ==1.8.2
Requires-Dist: certifi ==2024.7.4
Requires-Dist: charset-normalizer ==3.3.2
Requires-Dist: click ==8.1.7
Requires-Dist: exceptiongroup ==1.2.2
Requires-Dist: Flask ==3.0.3
Requires-Dist: frozenlist ==1.4.1
Requires-Dist: h11 ==0.14.0
Requires-Dist: h2 ==4.1.0
Requires-Dist: hpack ==4.0.0
Requires-Dist: Hypercorn ==0.17.3
Requires-Dist: hyperframe ==6.0.1
Requires-Dist: idna ==3.7
Requires-Dist: itsdangerous ==2.2.0
Requires-Dist: Jinja2 ==3.1.4
Requires-Dist: MarkupSafe ==2.1.5
Requires-Dist: multidict ==6.0.5
Requires-Dist: priority ==2.0.0
Requires-Dist: Quart ==0.19.6
Requires-Dist: requests ==2.32.3
Requires-Dist: taskgroup ==0.0.0a4
Requires-Dist: tomli ==2.0.1
Requires-Dist: typing-extensions ==4.12.2
Requires-Dist: urllib3 ==2.2.2
Requires-Dist: Werkzeug ==3.0.3
Requires-Dist: wsproto ==1.2.0
Requires-Dist: xmltodict ==0.13.0
Requires-Dist: yarl ==1.9.4
Provides-Extra: dev
Requires-Dist: build ; extra == 'dev'
Requires-Dist: twine ; extra == 'dev'
